mokaccino-0.6.0.dist-info/METADATA
mokaccino-0.6.0.dist-info/WHEEL
mokaccino/__init__.py
mokaccino/__init__.pyi
mokaccino/mokaccino.cpython-311-aarch64-linux-gnu.so
mokaccino/py.typed
mokaccino-0.6.0.dist-info/RECORD
