Metadata-Version: 2.4
Name: mokaccino
Version: 0.6.0
Classifier: Programming Language :: Rust
Classifier: Programming Language :: Python :: Implementation :: CPython
Classifier: Programming Language :: Python :: Implementation :: PyPy
Classifier: Development Status :: 4 - Beta
Classifier: Topic :: Software Development :: Libraries
Requires-Dist: pytest ; extra == 'dev'
Provides-Extra: dev
Home-Page: https://github.com/jeteve/mokaccino_py
Requires-Python: >=3.8
Project-URL: Documentation, https://github.com/jeteve/mokaccino_py#readme
Project-URL: Issues, https://github.com/jeteve/mokaccino_py/issues
Project-URL: Source, https://github.com/jeteve/mokaccino_py
